AUTHORS.rst
CHANGES.rst
LICENSE.txt
MANIFEST.in
README.rst
setup.py
django_pgcrypto_expressions.egg-info/PKG-INFO
django_pgcrypto_expressions.egg-info/SOURCES.txt
django_pgcrypto_expressions.egg-info/dependency_links.txt
django_pgcrypto_expressions.egg-info/not-zip-safe
django_pgcrypto_expressions.egg-info/requires.txt
django_pgcrypto_expressions.egg-info/top_level.txt
pgcrypto_expressions/__init__.py
pgcrypto_expressions/fields.py
pgcrypto_expressions/funcs.py
pgcrypto_expressions/test/__init__.py
pgcrypto_expressions/test/models.py
pgcrypto_expressions/test/settings.py
pgcrypto_expressions/test/test_fields.py
pgcrypto_expressions/test/test_funcs.py
pgcrypto_expressions/test/utils.py