Metadata-Version: 1.1
Name: django-pgcrypto-expressions
Version: 0.1
Summary: PGCrypto support for Django 1.8+
Home-page: https://github.com/orcasgit/django-pgcrypto-expressions/
Author: ORCAS, Inc
Author-email: orcastech@orcasinc.com
License: UNKNOWN
Platform: UNKNOWN
Classifier: Development Status :: 3 - Alpha
Classifier: Environment :: Web Environment
Classifier: Intended Audience :: Developers
Classifier: License :: OSI Approved :: BSD License
Classifier: Operating System :: OS Independent
Classifier: Programming Language :: Python
Classifier: Programming Language :: Python :: 2.6
Classifier: Programming Language :: Python :: 2.7
Classifier: Programming Language :: Python :: 3
Classifier: Programming Language :: Python :: 3.2
Classifier: Programming Language :: Python :: 3.3
Classifier: Framework :: Django
